multiheats/__init__.py
multiheats/constants.py
multiheats/create_profiles.py
multiheats/main.py
multiheats/solar_flux.py
multiheats/solvers.py
multiheats/visualise.py
multiheats-0.402.dist-info/COPYING
multiheats-0.402.dist-info/METADATA
multiheats-0.402.dist-info/WHEEL
multiheats-0.402.dist-info/top_level.txt
multiheats-0.402.dist-info/RECORD
