Metadata-Version: 2.1
Name: multiheats
Version: 0.402
Summary: MultIHeaTS is a Multi-layered Implicit Heat Transfer Solver.
Project-URL: Homepage, https://gitlab.dsi.universite-paris-saclay.fr/cyril.mergny/multiheats/
License-File: COPYING
Requires-Dist: wheel
Requires-Dist: ipython
Requires-Dist: pytest
Requires-Dist: numpy
Requires-Dist: matplotlib
Requires-Dist: scipy
Requires-Dist: pandas
Requires-Dist: tqdm
Requires-Dist: xlrd
